iglesia/__init__.py
iglesia/certificates.py
iglesia/helpers.py
iglesia/logger.py
iglesia/utils.py
radiopadre_client/__init__.py
radiopadre_client/config.py
radiopadre_client/default_config.py
radiopadre_client/kube.py
radiopadre_client/notebooks.py
radiopadre_client/remote.py
radiopadre_client/server.py
radiopadre_client/sessions.py
radiopadre_client/backends/__init__.py
radiopadre_client/backends/backend_utils.py
radiopadre_client/backends/docker.py
radiopadre_client/backends/singularity.py
radiopadre_client/backends/venv.py
radiopadre_client-1.2.4.data/scripts/run-radiopadre
radiopadre_client-1.2.4.dist-info/licenses/LICENSE
radiopadre_client-1.2.4.dist-info/METADATA
radiopadre_client-1.2.4.dist-info/WHEEL
radiopadre_client-1.2.4.dist-info/top_level.txt
radiopadre_client-1.2.4.dist-info/RECORD
