Metadata-Version: 2.4
Name: radiopadre-client
Version: 1.2.4
Summary: Radiopadre client-side script
Home-page: http://github.com/ratt-ru/radiopadre-client
Author: Oleg Smirnov
Author-email: osmirnov@gmail.com
License: MIT
Keywords: ipython notebook fits dataset resultset visualisation
Classifier: Development Status :: 5 - Production/Stable
Classifier: Topic :: Utilities
Classifier: License :: OSI Approved :: MIT License
Classifier: Programming Language :: Python :: 3
Classifier: Programming Language :: Python :: 3.9
Classifier: Programming Language :: Python :: 3.10
Classifier: Programming Language :: Python :: 3.11
Classifier: Programming Language :: Python :: 3.12
Classifier: Programming Language :: Python :: 3.13
Requires-Python: >=3.9
License-File: LICENSE
Requires-Dist: six
Requires-Dist: psutil
Requires-Dist: rich
Dynamic: author
Dynamic: author-email
Dynamic: classifier
Dynamic: description
Dynamic: home-page
Dynamic: keywords
Dynamic: license
Dynamic: license-file
Dynamic: requires-dist
Dynamic: requires-python
Dynamic: summary
